panda_pytest_assertions/__init__.py
panda_pytest_assertions/py.typed
panda_pytest_assertions/assert_context/__init__.py
panda_pytest_assertions/assert_context/_assert_context.py
panda_pytest_assertions/assert_object/__init__.py
panda_pytest_assertions/assert_object/_assert_object.py
panda_pytest_assertions/assert_object/_protocols.py
panda_pytest_assertions/assert_object/_asserter_factories/__init__.py
panda_pytest_assertions/assert_object/_asserter_factories/asserter_factory.py
panda_pytest_assertions/assert_object/_asserter_factories/built_in_asserter_factory.py
panda_pytest_assertions/assert_object/_converters/__init__.py
panda_pytest_assertions/assert_object/_converters/expectation_from_yaml.py
panda_pytest_assertions/assert_object/_converters/expectation_to_yaml.py
panda_pytest_assertions/assert_object/_expectation_modificators/__init__.py
panda_pytest_assertions/assert_object/_expectation_modificators/identity.py
panda_pytest_assertions/assert_object/_expectation_modificators/is_type.py
panda_pytest_assertions/assert_object/_expectation_modificators/mapping_subset.py
panda_pytest_assertions/assert_object/_expectation_modificators/object_attibutes.py
panda_pytest_assertions/assert_object/_expectation_modificators/stringified.py
panda_pytest_assertions/assert_object/_expectation_modificators/unordered.py
panda_pytest_assertions/assert_object/_expectation_modificators/with_type.py
panda_pytest_assertions/assert_object/_objects_asserters/__init__.py
panda_pytest_assertions/assert_object/_objects_asserters/asserter.py
panda_pytest_assertions/assert_object/_objects_asserters/equality_asserter.py
panda_pytest_assertions/assert_object/_objects_asserters/identity_asserter.py
panda_pytest_assertions/assert_object/_objects_asserters/is_type_asserter.py
panda_pytest_assertions/assert_object/_objects_asserters/mapping_asserter.py
panda_pytest_assertions/assert_object/_objects_asserters/mapping_subset_asserter.py
panda_pytest_assertions-0.3.0.dist-info/METADATA
panda_pytest_assertions-0.3.0.dist-info/WHEEL
panda_pytest_assertions-0.3.0.dist-info/licenses/LICENSE
panda_pytest_assertions-0.3.0.dist-info/licenses/NOTICE
panda_pytest_assertions-0.3.0.dist-info/RECORD
